pople/__init__.py
pople/calculator.py
pople/energy_corrections.py
pople/orca_g4mp2.py
pople/orca_g4mp2_ctrl.py
pople/orca_printbas.py
pople/orca_run.py
pople/params_atomic.py
pople/params_spinorbit.py
pople/params_thermal.py
pople/principal_coord.py
pople/uniqatoms.py
pople/utilities.py
pople/basis/GFHFB3
pople/basis/GFHFB4
pople/basis/GTBAS1
pople/basis/GTBAS1atm
pople/basis/GTBAS3
pople/basis/GTMP2largeXP
pople/basis/__init__.py
pople/tests/__init__.py
pople/tests/test_001_enthalpy_H2/ORCA.inp
pople/tests/test_001_enthalpy_H2/ORCA.out
pople/tests/test_001_enthalpy_H2/Thermochemistry.out
pople/tests/test_001_enthalpy_H2/__init__.py
pople/tests/test_001_enthalpy_H2/inp.py
pople/tests/test_002_ionizationenergy_H2O/ORCA.inp
pople/tests/test_002_ionizationenergy_H2O/ORCA.out
pople/tests/test_002_ionizationenergy_H2O/Thermochemistry.out
pople/tests/test_002_ionizationenergy_H2O/__init__.py
pople/tests/test_002_ionizationenergy_H2O/inp.py
pople/tests/test_003_enthalpy_H2_frozen_geom/ORCA.inp
pople/tests/test_003_enthalpy_H2_frozen_geom/ORCA.out
pople/tests/test_003_enthalpy_H2_frozen_geom/Thermochemistry.out
pople/tests/test_003_enthalpy_H2_frozen_geom/__init__.py
pople/tests/test_003_enthalpy_H2_frozen_geom/inp.py
pople/tests/test_004_electronaffinity_Cl/ORCA.inp
pople/tests/test_004_electronaffinity_Cl/ORCA.out
pople/tests/test_004_electronaffinity_Cl/Thermochemistry.out
pople/tests/test_004_electronaffinity_Cl/__init__.py
pople/tests/test_004_electronaffinity_Cl/inp.py
pople/tests/test_005_protonaffinity_NH3/ORCA.inp
pople/tests/test_005_protonaffinity_NH3/ORCA.out
pople/tests/test_005_protonaffinity_NH3/Thermochemistry.out
pople/tests/test_005_protonaffinity_NH3/__init__.py
pople/tests/test_005_protonaffinity_NH3/inp.py
pople/tests/test_006_bindingenergy_HFdimer/ORCA.inp
pople/tests/test_006_bindingenergy_HFdimer/ORCA.out
pople/tests/test_006_bindingenergy_HFdimer/Thermochemistry.out
pople/tests/test_006_bindingenergy_HFdimer/__init__.py
pople-21.4.1.dist-info/LICENSE
pople-21.4.1.dist-info/METADATA
pople-21.4.1.dist-info/WHEEL
pople-21.4.1.dist-info/top_level.txt
pople-21.4.1.dist-info/RECORD
