Metadata-Version: 2.1
Name: pople
Version: 21.4.1
Summary: A toolkit for ab initio thermochemistry
Home-page: https://github.com/salinisenthil/pople_package
Author: Salini Senthil, Raghunathan Ramakrishnan
Author-email: salinis@tifrh.res.in
License: MIT License
Platform: UNKNOWN
Requires-Dist: numpy
